__init__.py
segmentation.py
utils.py
python_noveltysegmentation-0.1.0.dist-info/METADATA
python_noveltysegmentation-0.1.0.dist-info/WHEEL
python_noveltysegmentation-0.1.0.dist-info/top_level.txt
python_noveltysegmentation-0.1.0.dist-info/RECORD
