Metadata-Version: 2.4
Name: python-noveltysegmentation
Version: 0.1.0
Summary: Python implementation of Novelty Segmentation
Author-email: Balthazar Bujard <balthazar.bujard@gmail.com>
Requires-Python: >=3.10
Requires-Dist: numpy
Requires-Dist: librosa
Requires-Dist: scipy
